setup.py
jma/JMAHTMLParser.py
jma/__init__.py
jma/__main__.py
jma/jmalib.py
jma.egg-info/PKG-INFO
jma.egg-info/SOURCES.txt
jma.egg-info/dependency_links.txt
jma.egg-info/entry_points.txt
jma.egg-info/top_level.txt