Metadata-Version: 1.1
Name: jma
Version: 1.0.0
Summary: Data downloader from Japan Meteorological Agency
Home-page: https://bitbucket.org/i_kiwamu/jma_stat
Author: Kiwamu Ishikura
Author-email: ishikura.kiwamu@gmail.com
License: UNKNOWN
Download-URL: https://bitbucket.org/i_kiwamu/jma_stat/downloads/jma_stat_2.0.0.zip
Platform: UNKNOWN
Classifier: Programming Language :: Python
Classifier: Programming Language :: Python :: 3.3
Classifier: Programming Language :: Python :: 3.4
Classifier: Development Status :: 5 - Production/Stable
Classifier: Environment :: Console
Classifier: Intended Audience :: End Users/Desktop
Classifier: Intended Audience :: Science/Research
Classifier: License :: OSI Approved :: GNU General Public License v3 (GPLv3)
Classifier: Natural Language :: Japanese
Classifier: Operating System :: OS Independent
Classifier: Topic :: Scientific/Engineering
Classifier: Topic :: Utilities
